assert_element/__init__.py
assert_element/assert_element.py
assert_element-0.6.1.dist-info/AUTHORS.rst
assert_element-0.6.1.dist-info/LICENSE
assert_element-0.6.1.dist-info/METADATA
assert_element-0.6.1.dist-info/WHEEL
assert_element-0.6.1.dist-info/top_level.txt
assert_element-0.6.1.dist-info/RECORD
