Metadata-Version: 2.1
Name: assert-element
Version: 0.6.1
Summary: Simple TestCase assertion that finds element based on it's path and check if it equals with given content.
Home-page: https://github.com/PetrDlouhy/django-assert-element
Author: Petr Dlouhý
Author-email: petr.dlouhy@email.cz
License: MIT
Keywords: assert_element
Classifier: Development Status :: 3 - Alpha
Classifier: Framework :: Django :: 1.11
Classifier: Framework :: Django :: 2.1
Classifier: Intended Audience :: Developers
Classifier: License :: OSI Approved :: BSD License
Classifier: Natural Language :: English
Classifier: Programming Language :: Python :: 2
Classifier: Programming Language :: Python :: 2.7
Classifier: Programming Language :: Python :: 3
Classifier: Programming Language :: Python :: 3.5
Classifier: Programming Language :: Python :: 3.6
License-File: LICENSE
License-File: AUTHORS.rst
Requires-Dist: beautifulsoup4
